tunman/__init__.py
tunman/test/__init__.py
tunman/test/test_ipparser.py
tunman/test/test_manager.py
tunman/test/test_model_host_tunnel_definitions.py
tunman/tunman/app.py
tunman/tunman/exceptions.py
tunman/tunman/factory.py
tunman/tunman/interfaces.py
tunman/tunman/logger.py
tunman/tunman/model.py
tunman/tunman/notify.py
tunman/tunman/settings.py
tunman/tunman/ssh.py
tunman/tunman/validation.py
tunman/tunman/views.py
tunman/tunman/manager/__init__.py
tunman/tunman/manager/ssh.py
tunman/tunman/manager/sysprocess.py
tunman/tunman/network/__init__.py
tunman/tunman/network/ipparser.py
tunman/tunman/static/bootstrap.min.css
tunman/tunman/static/logo.png
tunman/tunman/templates/status.html.j2
tunman-3.1.1.dist-info/AUTHORS
tunman-3.1.1.dist-info/METADATA
tunman-3.1.1.dist-info/WHEEL
tunman-3.1.1.dist-info/entry_points.txt
tunman-3.1.1.dist-info/pbr.json
tunman-3.1.1.dist-info/top_level.txt
tunman-3.1.1.dist-info/RECORD
